vhip_light/__init__.py
vhip_light/balancer.py
vhip_light/contact.py
vhip_light/gravity.py
vhip_light/inverted_pendulum.py
vhip_light/plotter.py
vhip_light/point.py
vhip_light/pole_placement_balancer.py
vhip_light/process.py
vhip_light/pusher.py
vhip_light/vhip_balancer.py
vhip_light/vhip_qp_balancer.py
vhip_light/vrp_balancer.py
vhip_light-1.0.0.dist-info/LICENSE
vhip_light-1.0.0.dist-info/WHEEL
vhip_light-1.0.0.dist-info/METADATA
vhip_light-1.0.0.dist-info/RECORD
