Metadata-Version: 2.1
Name: vhip_light
Version: 1.0.0
Summary: Variable-height inverted pendulum balancing in Python.
Keywords: inverse,kinematics,pinocchio
Author-email: Stéphane Caron <stephane.caron@normalesup.org>
Maintainer-email: Stéphane Caron <stephane.caron@normalesup.org>
Requires-Python: >=3.8
Classifier: Development Status :: 5 - Production/Stable
Classifier: Framework :: Robot Framework :: Library
Classifier: Intended Audience :: Developers
Classifier: Intended Audience :: Science/Research
Classifier: License :: OSI Approved :: GNU General Public License v3 (GPLv3)
Classifier: Programming Language :: Python :: 3
Classifier: Programming Language :: Python :: 3.10
Classifier: Programming Language :: Python :: 3.8
Classifier: Programming Language :: Python :: 3.9
Classifier: Topic :: Scientific/Engineering
Requires-Dist: loop-rate-limiters >=0.1.0
Requires-Dist: numpy >=1.19.0
Requires-Dist: pin >=2.6.3
Requires-Dist: qpsolvers >=2.5.0
Requires-Dist: quadprog >=0.1.11
Project-URL: Changelog, https://github.com/stephane-caron/vhip_light/blob/main/CHANGELOG.md
Project-URL: Documentation, https://stephane-caron.github.io/vhip_light/
Project-URL: Source, https://github.com/stephane-caron/vhip_light
Project-URL: Tracker, https://github.com/stephane-caron/vhip_light/issues
